.gitignore
README.md
setup.cfg
setup.py
.github/workflows/python-publish.yml
examples/content_moderation/acs_mlflow_model.ipynb
src/mlspells/__init__.py
src/mlspells.egg-info/PKG-INFO
src/mlspells.egg-info/SOURCES.txt
src/mlspells.egg-info/dependency_links.txt
src/mlspells.egg-info/requires.txt
src/mlspells.egg-info/top_level.txt
src/mlspells/base/__init__.py
src/mlspells/base/async_tasks.py
src/mlspells/base/sklearn/composition.py
src/mlspells/composition/transformations.py
src/mlspells/featuring/__init__.py
src/mlspells/featuring/latent.py
src/mlspells/featuring/tabular.py
src/mlspells/featuring/ts.py
src/mlspells/operationalize/__init__.py
src/mlspells/operationalize/models/__init__.py
src/mlspells/operationalize/models/ensembles.py
src/mlspells/operationalize/models/moderation.py
src/mlspells/operationalize/models/monitoring.py