Metadata-Version: 2.1
Name: mlspells
Version: 0.0.1
Summary: An army of ML tools to improve productivy
Home-page: https://github.com/santiagxf/mlspells
Author: Facundo Santiago
License: UNKNOWN
Platform: UNKNOWN
Classifier: Programming Language :: Python :: 3
Classifier: License :: OSI Approved :: MIT License
Classifier: Operating System :: OS Independent
Requires-Python: >=3.8
